{
  "nodes": [
    {
      "id": "andrew ng",
      "type": "Person",
      "description": "Andrew Ng is a British-American computer scientist and entrepreneur, known for his work in artificial intelligence and machine learning.",
      "x": 612.2586153702905,
      "y": 133.22554525052672,
      "expanded": true,
      "fetchingImage": false,
      "index": 0,
      "vy": -0.0022858028901502443,
      "vx": -0.009249274840897923,
      "isLoading": false,
      "fx": null,
      "fy": null,
      "imageUrl": "https://upload.wikimedia.org/wikipedia/commons/thumb/2/20/Andrew_Ng_at_TechCrunch_Disrupt_SF_2017.jpg/500px-Andrew_Ng_at_TechCrunch_Disrupt_SF_2017.jpg",
      "imageChecked": true
    },
    {
      "id": "sebastian thrun",
      "type": "Person",
      "description": "German-American entrepreneur, educator, and computer scientist.",
      "x": 808.1060879965797,
      "y": 588.655523566508,
      "expanded": true,
      "fetchingImage": false,
      "index": 1,
      "vy": -0.0004392218620762559,
      "vx": 0.00042329706075244083,
      "isLoading": false,
      "fx": null,
      "fy": null,
      "imageUrl": "https://upload.wikimedia.org/wikipedia/commons/thumb/7/71/Sebastian_Thrun_by_Christopher_Michel_-_6.jpg/500px-Sebastian_Thrun_by_Christopher_Michel_-_6.jpg",
      "imageChecked": true
    },
    {
      "id": "Stanford AI Lab",
      "type": "Organization",
      "description": "A research laboratory at Stanford University focusing on artificial intelligence.",
      "year": 2009,
      "x": 680.1059549598173,
      "y": 378.75136681301564,
      "index": 2,
      "vy": 0.0035247079086729496,
      "vx": -0.00793105466599548,
      "fetchingImage": false,
      "imageUrl": "https://upload.wikimedia.org/wikipedia/commons/thumb/e/ef/The_Stanford_Arm.jpg/500px-The_Stanford_Arm.jpg",
      "imageChecked": true,
      "isLoading": false
    },
    {
      "id": "Coursera",
      "type": "Company",
      "description": "Co-founded an online education technology company.",
      "year": 2012,
      "x": 514.8616237851543,
      "y": -102.27319607550062,
      "index": 3,
      "vy": -0.0079571730081858,
      "vx": -0.003878880863983544,
      "fetchingImage": false,
      "imageUrl": "https://upload.wikimedia.org/wikipedia/en/8/8f/Coursera_homepage.png",
      "imageChecked": true,
      "isLoading": false
    },
    {
      "id": "Baidu Artificial Intelligence Group",
      "type": "Organization",
      "description": "Served as Chief Scientist, building Baidu's Artificial Intelligence Group.",
      "year": 2014,
      "x": 643.7232619196265,
      "y": -83.74939307638606,
      "index": 4,
      "vy": -0.00403131347788805,
      "vx": -0.0041873800856959235,
      "fetchingImage": false,
      "imageUrl": "https://upload.wikimedia.org/wikipedia/commons/thumb/e/e4/Timeline-of-AI-generated-faces.png/500px-Timeline-of-AI-generated-faces.png",
      "imageChecked": true,
      "isLoading": false
    },
    {
      "id": "DeepLearning.AI",
      "type": "Company",
      "description": "Co-founded an online education company focused on deep learning.",
      "year": 2017,
      "x": 819.6017411315831,
      "y": 61.64951079792447,
      "index": 5,
      "vy": -0.0009748473092965565,
      "vx": -0.008714497517957708,
      "fetchingImage": false,
      "imageUrl": "https://upload.wikimedia.org/wikipedia/commons/thumb/7/77/Raspberry_Pi_5_Hailo_AI_Accelerator_Module.jpg/500px-Raspberry_Pi_5_Hailo_AI_Accelerator_Module.jpg",
      "imageChecked": true,
      "isLoading": false
    },
    {
      "id": "Landing AI",
      "type": "Company",
      "description": "Founded a company providing AI-powered SaaS products.",
      "year": 2017,
      "x": 861.9832574413929,
      "y": 184.56629333980277,
      "index": 6,
      "vy": -0.001499470947229676,
      "vx": -0.008541971986853055,
      "fetchingImage": false,
      "imageUrl": "https://upload.wikimedia.org/wikipedia/commons/thumb/2/20/Andrew_Ng_at_TechCrunch_Disrupt_SF_2017.jpg/500px-Andrew_Ng_at_TechCrunch_Disrupt_SF_2017.jpg",
      "imageChecked": true,
      "isLoading": false
    },
    {
      "id": "AI Fund",
      "type": "Investment Fund",
      "description": "Launched and heads an investment fund for artificial intelligence startups.",
      "year": 2018,
      "x": 487.5557415788592,
      "y": 141.48174122729918,
      "index": 7,
      "vy": 0.0006712488259894335,
      "vx": -0.009600397412965884,
      "fetchingImage": false,
      "imageUrl": "https://upload.wikimedia.org/wikipedia/commons/thumb/1/1f/Raspberry_Pi_AI_Kit_for_Raspberry_Pi_5_complete_Kit_07.jpg/500px-Raspberry_Pi_AI_Kit_for_Raspberry_Pi_5_complete_Kit_07.jpg",
      "imageChecked": true,
      "isLoading": false
    },
    {
      "id": "Amazon Board of Directors Appointment",
      "type": "Event",
      "description": "Appointed to the board of directors of Amazon.",
      "year": 2024,
      "x": 770.8988391031975,
      "y": 284.5631737189572,
      "index": 8,
      "vy": -0.0014359265495755519,
      "vx": -0.006757618503553968,
      "fetchingImage": false,
      "imageUrl": "https://upload.wikimedia.org/wikipedia/commons/thumb/d/de/Annual_report_of_the_Board_of_Regents_of_the_Smithsonian_Institution_%28IA_annualreportofbo1879smit%29.pdf/page1-500px-Annual_report_of_the_Board_of_Regents_of_the_Smithsonian_Institution_%28IA_annualreportofbo1879smit%29.pdf.jpg",
      "imageChecked": true,
      "isLoading": false
    },
    {
      "id": "Stanley (Robotic Vehicle)",
      "type": "Project",
      "description": "Led development of the autonomous vehicle Stanley, which won the DARPA Grand Challenge.",
      "year": 2005,
      "x": 894.641452862335,
      "y": 420.28870328383186,
      "index": 9,
      "vy": 0.0004825428583185138,
      "vx": 0.005291868770490572,
      "fetchingImage": false,
      "imageUrl": "https://upload.wikimedia.org/wikipedia/commons/thumb/3/3e/Stanley2.JPG/500px-Stanley2.JPG",
      "imageChecked": true,
      "isLoading": false
    },
    {
      "id": "DARPA Grand Challenge",
      "type": "Event",
      "description": "Competition won by the autonomous vehicle Stanley, developed by his team.",
      "year": 2005,
      "x": 730.653664104925,
      "y": 686.6708207826771,
      "index": 10,
      "vy": 0.0013887965293072505,
      "vx": 0.00040059355933540946,
      "fetchingImage": false,
      "imageUrl": "https://upload.wikimedia.org/wikipedia/commons/thumb/e/e3/DARPA_Launch_Challenge.png/500px-DARPA_Launch_Challenge.png",
      "imageChecked": true,
      "isLoading": false
    },
    {
      "id": "Junior (Robotic Vehicle)",
      "type": "Project",
      "description": "Led development of the autonomous vehicle Junior, which placed second at the DARPA Urban Challenge.",
      "year": 2007,
      "x": 602.4921018456045,
      "y": 664.8892361989458,
      "index": 11,
      "vy": 0.0020140302571690664,
      "vx": 0.000136846297965176,
      "fetchingImage": false,
      "imageUrl": "https://upload.wikimedia.org/wikipedia/commons/thumb/7/71/Sebastian_Thrun_by_Christopher_Michel_-_6.jpg/500px-Sebastian_Thrun_by_Christopher_Michel_-_6.jpg",
      "imageChecked": true,
      "isLoading": false
    },
    {
      "id": "National Academy of Engineering Election",
      "type": "Award",
      "description": "Elected into the National Academy of Engineering for contributions to computer science and robotics.",
      "year": 2007,
      "x": 773.9562642216174,
      "y": 468.56886443975674,
      "index": 12,
      "vy": -0.004622642588602079,
      "vx": 0.0028471996046956364,
      "fetchingImage": false,
      "imageUrl": "https://upload.wikimedia.org/wikipedia/commons/thumb/e/e0/Dan_Mote%2C_President_of_the_National_Academy_of_Engineering_%2816307312803%29.jpg/500px-Dan_Mote%2C_President_of_the_National_Academy_of_Engineering_%2816307312803%29.jpg",
      "imageChecked": true,
      "isLoading": false
    },
    {
      "id": "Google Self-Driving Car Project",
      "type": "Project",
      "description": "Co-founded and led the development of Google's autonomous vehicle initiative.",
      "year": 2009,
      "x": 1005.9089467713965,
      "y": 487.4844738355724,
      "index": 13,
      "vy": 0.0028191115043255054,
      "vx": 0.004334965544778438,
      "fetchingImage": false,
      "imageUrl": "https://upload.wikimedia.org/wikipedia/commons/thumb/1/1b/Google%27s_Lexus_RX_450h_Self-Driving_Car.jpg/500px-Google%27s_Lexus_RX_450h_Self-Driving_Car.jpg",
      "imageChecked": true,
      "isLoading": false
    },
    {
      "id": "Google X",
      "type": "Project",
      "description": "Co-founded Google's semi-secret research and development facility.",
      "year": 2010,
      "x": 592.1021353468567,
      "y": 474.37813784052565,
      "index": 14,
      "vy": 0.006043363103650383,
      "vx": -0.006562724748604835,
      "fetchingImage": false,
      "imageUrl": "https://upload.wikimedia.org/wikipedia/commons/thumb/2/2c/Google_Loon_-_Launch_Event.jpg/500px-Google_Loon_-_Launch_Event.jpg",
      "imageChecked": true,
      "isLoading": false
    },
    {
      "id": "Kitty Hawk Corporation",
      "type": "Project",
      "description": "Co-founder and chief executive officer of the electric aircraft company.",
      "year": 2010,
      "x": 651.8721045312722,
      "y": 790.0571679334469,
      "index": 15,
      "vy": 0.0019659010069876734,
      "vx": 0.00027602575889801957,
      "fetchingImage": false,
      "imageUrl": "https://upload.wikimedia.org/wikipedia/commons/thumb/1/1b/Kitty_Hawk_Flyer_%28cn_096%29_%286-17-2025%29.jpg/500px-Kitty_Hawk_Flyer_%28cn_096%29_%286-17-2025%29.jpg",
      "imageChecked": true,
      "isLoading": false
    },
    {
      "id": "Udacity",
      "type": "Project",
      "description": "Co-founder and chairman of the online education platform.",
      "year": 2011,
      "x": 781.5032244900015,
      "y": 806.3168568027739,
      "index": 16,
      "vy": 0.0010601621996592905,
      "vx": 0.0009827045714002347,
      "fetchingImage": false,
      "imageUrl": "https://upload.wikimedia.org/wikipedia/commons/thumb/6/66/Sebastian_Thrun_at_IAA_2019_IMG_0893.jpg/500px-Sebastian_Thrun_at_IAA_2019_IMG_0893.jpg",
      "imageChecked": true,
      "isLoading": false
    },
    {
      "id": "Policy Search for Motor Control with Reinforcement Learning",
      "type": "Academic Paper",
      "description": "Co-authored seminal paper in robotics and reinforcement learning",
      "year": 2003,
      "x": 734.3765555217384,
      "y": 159.8202587247402,
      "index": 17,
      "vy": -0.0013059050733123733,
      "vx": -0.008965838638463465,
      "fetchingImage": false,
      "imageUrl": "https://upload.wikimedia.org/wikipedia/commons/thumb/1/1d/A_culture-free_performance_test_of_general_learning_ability._%28IA_culturefreeperfo00youn%29.pdf/page1-500px-A_culture-free_performance_test_of_general_learning_ability._%28IA_culturefreeperfo00youn%29.pdf.jpg",
      "imageChecked": true,
      "isLoading": false
    },
    {
      "id": "Autonomous Helicopter Flight via Reinforcement Learning",
      "type": "Academic Paper",
      "description": "Co-authored influential paper demonstrating complex robotic control",
      "year": 2004,
      "x": 515.4132740466559,
      "y": 268.4524814888055,
      "index": 18,
      "vy": 0.0003767192945206979,
      "vx": -0.007275224988357376,
      "fetchingImage": false,
      "imageUrl": "https://upload.wikimedia.org/wikipedia/commons/thumb/d/d9/USDA_Drone_poster.jpg/500px-USDA_Drone_poster.jpg",
      "imageChecked": true,
      "isLoading": false
    },
    {
      "id": "Stanford University CS229 Machine Learning Course",
      "type": "Educational Project",
      "description": "Developed and taught highly influential machine learning course",
      "year": 2009,
      "x": 433.3839667415305,
      "y": 23.31041636950148,
      "index": 19,
      "vy": -0.00044099699899516353,
      "vx": -0.007367902753453181,
      "fetchingImage": false,
      "imageUrl": "https://upload.wikimedia.org/wikipedia/commons/thumb/2/20/Andrew_Ng_at_TechCrunch_Disrupt_SF_2017.jpg/500px-Andrew_Ng_at_TechCrunch_Disrupt_SF_2017.jpg",
      "imageChecked": true,
      "isLoading": false
    },
    {
      "id": "Efficient Learning of Deep Boltzmann Machines",
      "type": "Academic Paper",
      "description": "Co-authored research on deep learning architectures",
      "year": 2012,
      "x": 777.1166981666317,
      "y": -61.23725640332477,
      "index": 20,
      "vy": -0.0011646147683800497,
      "vx": -0.006439615660379998,
      "fetchingImage": false,
      "imageUrl": "https://upload.wikimedia.org/wikipedia/commons/7/7a/Boltzmannexamplev1.png",
      "imageChecked": true,
      "isLoading": false
    },
    {
      "id": "Time Magazine's 100 Most Influential People",
      "type": "Recognition",
      "description": "Named in influential list for contributions to AI",
      "year": 2012,
      "x": 563.2819279370066,
      "y": 18.36556351243833,
      "index": 21,
      "vy": -0.006371044965768012,
      "vx": -0.0073862996211689295,
      "fetchingImage": false,
      "imageUrl": "https://upload.wikimedia.org/wikipedia/commons/thumb/6/6f/FDR-1944-Campaign-Portrait_%28cropped%29.jpg/500px-FDR-1944-Campaign-Portrait_%28cropped%29.jpg",
      "imageChecked": true,
      "isLoading": false
    },
    {
      "id": "Fast Company's Most Creative People",
      "type": "Recognition",
      "description": "Named in influential list for creative contributions to technology",
      "year": 2014,
      "x": 644.5826037587017,
      "y": 253.80234521536414,
      "index": 22,
      "vy": 0.0009863277667978045,
      "vx": -0.007146941075768243,
      "fetchingImage": false,
      "imageUrl": "https://upload.wikimedia.org/wikipedia/commons/thumb/2/20/Andrew_Ng_at_TechCrunch_Disrupt_SF_2017.jpg/500px-Andrew_Ng_at_TechCrunch_Disrupt_SF_2017.jpg",
      "imageChecked": true,
      "isLoading": false
    },
    {
      "id": "Time100 AI Most Influential People",
      "type": "Recognition",
      "description": "Named in influential list for leadership in AI",
      "year": 2023,
      "x": 691.9438056643683,
      "y": 36.963497980890104,
      "index": 23,
      "vy": -0.002207842828412302,
      "vx": -0.007956329686423904,
      "fetchingImage": false,
      "imageUrl": "https://upload.wikimedia.org/wikipedia/commons/thumb/2/20/Andrew_Ng_at_TechCrunch_Disrupt_SF_2017.jpg/500px-Andrew_Ng_at_TechCrunch_Disrupt_SF_2017.jpg",
      "imageChecked": true,
      "isLoading": false
    },
    {
      "id": "Ben-Hur: A Tale of the Christ",
      "type": "Book",
      "description": "Lew Wallace's original novel featuring the character Judah Ben-Hur",
      "year": 1880,
      "x": 932.8164689554959,
      "y": 594.9934341446477,
      "expanded": false,
      "index": 24,
      "vy": 0.0017206801423586635,
      "vx": 0.002813870220623409,
      "fetchingImage": false,
      "imageUrl": "https://upload.wikimedia.org/wikipedia/en/e/ed/Ben_Hur_2010.jpg",
      "imageChecked": true
    },
    {
      "id": "Ben-Hur (1907 film)",
      "type": "Movie",
      "description": "Early American silent film adaptation of the novel",
      "year": 1907,
      "x": 912.9174018139424,
      "y": 821.0100112202741,
      "expanded": false,
      "index": 25,
      "vy": 0.0019365230819068666,
      "vx": 0.0007265880515402016,
      "fetchingImage": false,
      "imageUrl": "https://upload.wikimedia.org/wikipedia/commons/thumb/d/de/Ben_Hur_%281907%29_film..jpg/500px-Ben_Hur_%281907%29_film..jpg",
      "imageChecked": true
    },
    {
      "id": "Ben-Hur: A Tale of the Christ (1925 film)",
      "type": "Movie",
      "description": "Epic American silent film adaptation of the novel",
      "year": 1925,
      "x": 859.6499785895774,
      "y": 702.4287430058133,
      "expanded": false,
      "index": 26,
      "vy": 0.0014344098002961384,
      "vx": 0.0017148244294382243,
      "fetchingImage": false,
      "imageUrl": "https://upload.wikimedia.org/wikipedia/commons/thumb/6/63/Ben-Hur-1925.jpg/500px-Ben-Hur-1925.jpg",
      "imageChecked": true
    },
    {
      "id": "Ben-Hur (1959 film)",
      "type": "Movie",
      "description": "Critically acclaimed epic film adaptation of the novel",
      "year": 1959,
      "x": 685.468413939588,
      "y": 564.8208401203339,
      "expanded": false,
      "index": 27,
      "vy": 0.0008272503371432546,
      "vx": -0.0011578899768067818,
      "fetchingImage": false,
      "imageUrl": "https://upload.wikimedia.org/wikipedia/commons/thumb/7/74/Ben_hur_1959_poster.jpg/500px-Ben_hur_1959_poster.jpg",
      "imageChecked": true
    },
    {
      "id": "Ben-Hur (2003 animated film)",
      "type": "Movie",
      "description": "Animated film adaptation of the novel",
      "year": 2003,
      "x": 989.2833998020094,
      "y": 712.1094179319607,
      "expanded": false,
      "index": 28,
      "vy": 0.001600805436486439,
      "vx": 0.001886332216277007,
      "fetchingImage": false,
      "imageUrl": "https://upload.wikimedia.org/wikipedia/en/3/36/Ben_Hur_FilmPoster.jpeg",
      "imageChecked": true
    },
    {
      "id": "Ben-Hur (2016 film)",
      "type": "Movie",
      "description": "Modern live-action film adaptation of the novel",
      "year": 2016,
      "x": 1062.4463070248703,
      "y": 604.6317585745389,
      "expanded": false,
      "index": 29,
      "vy": 0.0022227888760243857,
      "vx": 0.0031041495714119764,
      "fetchingImage": false,
      "imageUrl": "https://upload.wikimedia.org/wikipedia/en/0/0a/Ben-Hur_2016_poster.png",
      "imageChecked": true
    }
  ],
  "links": [
    {
      "source": "andrew ng",
      "target": "Stanford AI Lab",
      "id": "andrew ng-Stanford AI Lab",
      "label": "2009"
    },
    {
      "source": "andrew ng",
      "target": "Google Brain",
      "id": "andrew ng-Google Brain",
      "label": "2011"
    },
    {
      "source": "andrew ng",
      "target": "Coursera",
      "id": "andrew ng-Coursera",
      "label": "2012"
    },
    {
      "source": "andrew ng",
      "target": "Baidu Artificial Intelligence Group",
      "id": "andrew ng-Baidu Artificial Intelligence Group",
      "label": "2014"
    },
    {
      "source": "andrew ng",
      "target": "DeepLearning.AI",
      "id": "andrew ng-DeepLearning.AI",
      "label": "2017"
    },
    {
      "source": "andrew ng",
      "target": "Landing AI",
      "id": "andrew ng-Landing AI",
      "label": "2017"
    },
    {
      "source": "andrew ng",
      "target": "AI Fund",
      "id": "andrew ng-AI Fund",
      "label": "2018"
    },
    {
      "source": "andrew ng",
      "target": "Amazon Board of Directors Appointment",
      "id": "andrew ng-Amazon Board of Directors Appointment",
      "label": "2024"
    },
    {
      "source": "Stanford AI Lab",
      "target": "sebastian thrun",
      "id": "Stanford AI Lab-sebastian thrun",
      "label": "Sebastian Thrun was a Professor of Computer Science at Stanford University, the institution housing the Stanford AI Lab, and a leading researcher in artificial intelligence and robotics."
    },
    {
      "source": "sebastian thrun",
      "target": "Stanley (Robotic Vehicle)",
      "id": "sebastian thrun-Stanley (Robotic Vehicle)",
      "label": "2005"
    },
    {
      "source": "sebastian thrun",
      "target": "DARPA Grand Challenge",
      "id": "sebastian thrun-DARPA Grand Challenge",
      "label": "2005"
    },
    {
      "source": "sebastian thrun",
      "target": "Junior (Robotic Vehicle)",
      "id": "sebastian thrun-Junior (Robotic Vehicle)",
      "label": "2007"
    },
    {
      "source": "sebastian thrun",
      "target": "National Academy of Engineering Election",
      "id": "sebastian thrun-National Academy of Engineering Election",
      "label": "2007"
    },
    {
      "source": "sebastian thrun",
      "target": "Google Self-Driving Car Project",
      "id": "sebastian thrun-Google Self-Driving Car Project",
      "label": "2009"
    },
    {
      "source": "sebastian thrun",
      "target": "Google X",
      "id": "sebastian thrun-Google X",
      "label": "2010"
    },
    {
      "source": "sebastian thrun",
      "target": "Kitty Hawk Corporation",
      "id": "sebastian thrun-Kitty Hawk Corporation",
      "label": "2010"
    },
    {
      "source": "sebastian thrun",
      "target": "Udacity",
      "id": "sebastian thrun-Udacity",
      "label": "2011"
    },
    {
      "source": "andrew ng",
      "target": "Policy Search for Motor Control with Reinforcement Learning",
      "id": "andrew ng-Policy Search for Motor Control with Reinforcement Learning",
      "label": "2003"
    },
    {
      "source": "andrew ng",
      "target": "Autonomous Helicopter Flight via Reinforcement Learning",
      "id": "andrew ng-Autonomous Helicopter Flight via Reinforcement Learning",
      "label": "2004"
    },
    {
      "source": "andrew ng",
      "target": "Stanford University CS229 Machine Learning Course",
      "id": "andrew ng-Stanford University CS229 Machine Learning Course",
      "label": "2009"
    },
    {
      "source": "andrew ng",
      "target": "Efficient Learning of Deep Boltzmann Machines",
      "id": "andrew ng-Efficient Learning of Deep Boltzmann Machines",
      "label": "2012"
    },
    {
      "source": "andrew ng",
      "target": "Time Magazine's 100 Most Influential People",
      "id": "andrew ng-Time Magazine's 100 Most Influential People",
      "label": "2012"
    },
    {
      "source": "andrew ng",
      "target": "Fast Company's Most Creative People",
      "id": "andrew ng-Fast Company's Most Creative People",
      "label": "2014"
    },
    {
      "source": "andrew ng",
      "target": "Time100 AI Most Influential People",
      "id": "andrew ng-Time100 AI Most Influential People",
      "label": "2023"
    },
    {
      "source": "sebastian thrun",
      "target": "Ben-Hur: A Tale of the Christ",
      "id": "sebastian thrun-Ben-Hur: A Tale of the Christ",
      "label": "1880"
    },
    {
      "source": "sebastian thrun",
      "target": "Ben-Hur (1907 film)",
      "id": "sebastian thrun-Ben-Hur (1907 film)",
      "label": "1907"
    },
    {
      "source": "sebastian thrun",
      "target": "Ben-Hur: A Tale of the Christ (1925 film)",
      "id": "sebastian thrun-Ben-Hur: A Tale of the Christ (1925 film)",
      "label": "1925"
    },
    {
      "source": "sebastian thrun",
      "target": "Ben-Hur (1959 film)",
      "id": "sebastian thrun-Ben-Hur (1959 film)",
      "label": "1959"
    },
    {
      "source": "sebastian thrun",
      "target": "Ben-Hur (2003 animated film)",
      "id": "sebastian thrun-Ben-Hur (2003 animated film)",
      "label": "2003"
    },
    {
      "source": "sebastian thrun",
      "target": "Ben-Hur (2016 film)",
      "id": "sebastian thrun-Ben-Hur (2016 film)",
      "label": "2016"
    }
  ],
  "searchMode": "connect",
  "exploreTerm": "The Godfather",
  "pathStart": "andrew ng",
  "pathEnd": "sebastian thrun",
  "isCompact": false,
  "isTimelineMode": false,
  "isTextOnly": false,
  "date": 1766456756850
}